flattener/__init__.py
flattener/flatten.py
flatten_nosql-2.2.dist-info/METADATA
flatten_nosql-2.2.dist-info/WHEEL
flatten_nosql-2.2.dist-info/license.txt
flatten_nosql-2.2.dist-info/top_level.txt
flatten_nosql-2.2.dist-info/RECORD
