Metadata-Version: 2.1
Name: flatten-nosql
Version: 2.2
Summary: This module converts NoSQL data to plain SQL data.
Home-page: https://github.com/proafxin/nosql-to-sql
Author: Masum Billal
Author-email: billalmasum93@gmail.com
License: MIT
Classifier: Programming Language :: Python :: 3
Classifier: License :: OSI Approved :: MIT License
Classifier: Operating System :: OS Independent
Requires-Python: >=3.6
License-File: license.txt
Requires-Dist: pandas
